{
  "version": "2.1.1",
  "enabled": true,
  "account": {
    "equity": 100944.59,
    "cash": 100944.59,
    "account_number": "PA3SACVCVUOH"
  },
  "principal_target": 100944.59,
  "savings": 0.0,
  "lifetime_realized_wins": 0,
  "lifetime_realized_losses": 0,
  "position_meta": {},
  "tickers_traded_this_cycle": [],
  "recent_alpaca_tickers": [],
  "orders": [],
  "orders_placed": [],
  "errors": [],
  "last_run": "2026-05-04T17:43:50.085629+00:00",
  "_flushed_at": "2026-05-04T17:43:50.085629+00:00",
  "_flush_note": "v4.1 hotfix: flushed all positions on 2026-05-04T17:43:50.085629+00:00. Principal target locked at $100,944.59 (post-flush equity)."
}