{
  "generated_at": "2026-04-30T22:06:11.741430+00:00",
  "config": {
    "max_single_position_pct": 0.25,
    "min_cash_buffer_pct": 0.0,
    "daily_drawdown_freeze_pct": 0.08,
    "daily_drawdown_unfreeze_pct": 0.04,
    "kill_weight_threshold": 0.85,
    "kill_min_calls": 15,
    "cohort_dd_threshold": 0.05,
    "cohort_dd_min_runs": 5,
    "min_reward_risk": 1.5,
    "max_risk_per_plan_pct": 0.02
  },
  "system": {
    "safe_mode": true,
    "safe_mode_reason": "Cohort average return -66.67% breached \u22125% safe-mode threshold. All agents holding existing positions; no new opens.",
    "safe_mode_since": "2026-04-30",
    "cohort_avg_return_pct": -66.666,
    "cohort_history": [
      {
        "date": "2026-04-30",
        "cohort_avg_return_pct": -66.666,
        "n_agents": 27
      },
      {
        "date": "2026-04-30",
        "cohort_avg_return_pct": -66.666,
        "n_agents": 27
      },
      {
        "date": "2026-04-30",
        "cohort_avg_return_pct": -66.666,
        "n_agents": 27
      },
      {
        "date": "2026-04-30",
        "cohort_avg_return_pct": -66.666,
        "n_agents": 27
      },
      {
        "date": "2026-04-30",
        "cohort_avg_return_pct": -66.666,
        "n_agents": 27
      },
      {
        "date": "2026-04-30",
        "cohort_avg_return_pct": -66.666,
        "n_agents": 27
      },
      {
        "date": "2026-04-30",
        "cohort_avg_return_pct": -66.666,
        "n_agents": 27
      },
      {
        "date": "2026-04-30",
        "cohort_avg_return_pct": -66.666,
        "n_agents": 27
      }
    ]
  },
  "agents": {
    "AEGIS": {
      "agent": "AEGIS",
      "frozen": false,
      "frozen_reason": "",
      "frozen_since": "",
      "last_equity": 0.0101,
      "peak_equity": 0.0101,
      "drawdown_pct": 0.0
    },
    "FORGE": {
      "agent": "FORGE",
      "frozen": false,
      "frozen_reason": "",
      "frozen_since": "",
      "last_equity": 0.0101,
      "peak_equity": 0.0101,
      "drawdown_pct": 0.0
    },
    "THUNDERHEAD": {
      "agent": "THUNDERHEAD",
      "frozen": true,
      "frozen_reason": "Performance below baseline: weight multiplier 0.81\u00d7 < 0.85\u00d7 (after 24 scored calls). Frozen until track record recovers.",
      "frozen_since": "2026-04-30",
      "last_equity": 0.0309,
      "peak_equity": 0.0309,
      "drawdown_pct": 0.0
    },
    "JADE": {
      "agent": "JADE",
      "frozen": false,
      "frozen_reason": "",
      "frozen_since": "",
      "last_equity": 0.0309,
      "peak_equity": 0.0309,
      "drawdown_pct": 0.0
    },
    "VEIL": {
      "agent": "VEIL",
      "frozen": true,
      "frozen_reason": "Performance below baseline: weight multiplier 0.85\u00d7 < 0.85\u00d7 (after 35 scored calls). Frozen until track record recovers.",
      "frozen_since": "2026-04-30",
      "last_equity": 0.0306,
      "peak_equity": 0.0306,
      "drawdown_pct": 0.0
    },
    "KESTREL": {
      "agent": "KESTREL",
      "frozen": true,
      "frozen_reason": "Performance below baseline: weight multiplier 0.83\u00d7 < 0.85\u00d7 (after 18 scored calls). Frozen until track record recovers.",
      "frozen_since": "2026-04-30",
      "last_equity": 0.7101,
      "peak_equity": 0.7101,
      "drawdown_pct": 0.0
    },
    "OBSIDIAN": {
      "agent": "OBSIDIAN",
      "frozen": false,
      "frozen_reason": "",
      "frozen_since": "",
      "last_equity": 0.032,
      "peak_equity": 0.032,
      "drawdown_pct": 0.0
    },
    "ZENITH": {
      "agent": "ZENITH",
      "frozen": true,
      "frozen_reason": "Performance below baseline: weight multiplier 0.75\u00d7 < 0.85\u00d7 (after 103 scored calls). Frozen until track record recovers.",
      "frozen_since": "2026-04-30",
      "last_equity": 0.0306,
      "peak_equity": 0.0306,
      "drawdown_pct": 0.0
    },
    "WEAVER": {
      "agent": "WEAVER",
      "frozen": true,
      "frozen_reason": "Performance below baseline: weight multiplier 0.83\u00d7 < 0.85\u00d7 (after 114 scored calls). Frozen until track record recovers.",
      "frozen_since": "2026-04-30",
      "last_equity": 0.0303,
      "peak_equity": 0.0303,
      "drawdown_pct": 0.0
    },
    "HEX": {
      "agent": "HEX",
      "frozen": true,
      "frozen_reason": "Performance below baseline: weight multiplier 0.75\u00d7 < 0.85\u00d7 (after 72 scored calls). Frozen until track record recovers.",
      "frozen_since": "2026-04-30",
      "last_equity": 0.0306,
      "peak_equity": 0.0306,
      "drawdown_pct": 0.0
    },
    "SYNTH": {
      "agent": "SYNTH",
      "frozen": true,
      "frozen_reason": "Performance below baseline: weight multiplier 0.75\u00d7 < 0.85\u00d7 (after 47 scored calls). Frozen until track record recovers.",
      "frozen_since": "2026-04-30",
      "last_equity": 0.0309,
      "peak_equity": 0.0309,
      "drawdown_pct": 0.0
    },
    "SPECK": {
      "agent": "SPECK",
      "frozen": false,
      "frozen_reason": "",
      "frozen_since": "",
      "last_equity": 0.0299,
      "peak_equity": 0.0299,
      "drawdown_pct": 0.0
    },
    "VESPA": {
      "agent": "VESPA",
      "frozen": false,
      "frozen_reason": "",
      "frozen_since": "",
      "last_equity": 0.0309,
      "peak_equity": 0.0309,
      "drawdown_pct": 0.0
    },
    "MAGUS": {
      "agent": "MAGUS",
      "frozen": false,
      "frozen_reason": "",
      "frozen_since": "",
      "last_equity": 0.01,
      "peak_equity": 0.01,
      "drawdown_pct": 0.0
    },
    "TALON": {
      "agent": "TALON",
      "frozen": false,
      "frozen_reason": "",
      "frozen_since": "",
      "last_equity": 0.01,
      "peak_equity": 0.01,
      "drawdown_pct": 0.0
    },
    "ATLAS": {
      "agent": "ATLAS",
      "frozen": false,
      "frozen_reason": "",
      "frozen_since": "",
      "last_equity": 0.01,
      "peak_equity": 0.01,
      "drawdown_pct": 0.0
    },
    "NIGHTSHADE": {
      "agent": "NIGHTSHADE",
      "frozen": false,
      "frozen_reason": "",
      "frozen_since": "",
      "last_equity": 10000.0,
      "peak_equity": 10000.0,
      "drawdown_pct": 0.0
    },
    "CICADA": {
      "agent": "CICADA",
      "frozen": false,
      "frozen_reason": "",
      "frozen_since": "",
      "last_equity": 10000.0,
      "peak_equity": 10000.0,
      "drawdown_pct": 0.0
    },
    "SHEPHERD": {
      "agent": "SHEPHERD",
      "frozen": false,
      "frozen_reason": "",
      "frozen_since": "",
      "last_equity": 10000.0,
      "peak_equity": 10000.0,
      "drawdown_pct": 0.0
    },
    "NOMAD": {
      "agent": "NOMAD",
      "frozen": false,
      "frozen_reason": "",
      "frozen_since": "",
      "last_equity": 10000.0,
      "peak_equity": 10000.0,
      "drawdown_pct": 0.0
    },
    "BARNACLE": {
      "agent": "BARNACLE",
      "frozen": false,
      "frozen_reason": "",
      "frozen_since": "",
      "last_equity": 10000.0,
      "peak_equity": 10000.0,
      "drawdown_pct": 0.0
    },
    "KESTREL+": {
      "agent": "KESTREL+",
      "frozen": false,
      "frozen_reason": "",
      "frozen_since": "",
      "last_equity": 10000.0,
      "peak_equity": 10000.0,
      "drawdown_pct": 0.0
    },
    "BARON": {
      "agent": "BARON",
      "frozen": false,
      "frozen_reason": "",
      "frozen_since": "",
      "last_equity": 0.031,
      "peak_equity": 0.031,
      "drawdown_pct": 0.0
    },
    "STEADFAST": {
      "agent": "STEADFAST",
      "frozen": false,
      "frozen_reason": "",
      "frozen_since": "",
      "last_equity": 0.031,
      "peak_equity": 0.031,
      "drawdown_pct": 0.0
    },
    "SPORTS_BRO": {
      "agent": "SPORTS_BRO",
      "frozen": false,
      "frozen_reason": "",
      "frozen_since": "",
      "last_equity": 10000.0,
      "peak_equity": 10000.0,
      "drawdown_pct": 0.0
    },
    "CONTRARIAN": {
      "agent": "CONTRARIAN",
      "frozen": false,
      "frozen_reason": "",
      "frozen_since": "",
      "last_equity": 10000.0,
      "peak_equity": 10000.0,
      "drawdown_pct": 0.0
    },
    "SHORT_ALPHA": {
      "agent": "SHORT_ALPHA",
      "frozen": false,
      "frozen_reason": "",
      "frozen_since": "",
      "last_equity": 10000.0,
      "peak_equity": 10000.0,
      "drawdown_pct": 0.0
    }
  },
  "summary": {
    "frozen_count": 7,
    "total_count": 27,
    "safe_mode": true
  }
}